setup.py
flaskhtmltemplates/__init__.py
flaskhtmltemplates.egg-info/PKG-INFO
flaskhtmltemplates.egg-info/SOURCES.txt
flaskhtmltemplates.egg-info/dependency_links.txt
flaskhtmltemplates.egg-info/top_level.txt