Metadata-Version: 1.0
Name: flaskhtmltemplates
Version: 1.0.0
Summary: A way to easily template html documents with flask/http.server
Home-page: UNKNOWN
Author: UNKNOWN
Author-email: UNKNOWN
License: UNKNOWN
Platform: UNKNOWN
